instrument_models/__init__.py
instrument_models/cassini_iss.py
instrument_models/get_wavelength.py
instrument_models/instrument.py
instrument_models/mastcam.py
instrument_models/pancam.py
pdsspect/__init__.py
pdsspect/basic.py
pdsspect/histogram.py
pdsspect/pan_view.py
pdsspect/pds_image_view_canvas.py
pdsspect/pdsspect.py
pdsspect/pdsspect_image_set.py
pdsspect/pdsspect_view.py
pdsspect/roi.py
pdsspect/roi_histogram.py
pdsspect/roi_line_plot.py
pdsspect/roi_plot.py
pdsspect/selection.py
pdsspect/set_wavelength.py
pdsspect/transforms.py
pdsspect/warningtimer.py
pdsspect-0.1.1.dist-info/DESCRIPTION.rst
pdsspect-0.1.1.dist-info/METADATA
pdsspect-0.1.1.dist-info/RECORD
pdsspect-0.1.1.dist-info/WHEEL
pdsspect-0.1.1.dist-info/entry_points.txt
pdsspect-0.1.1.dist-info/metadata.json
pdsspect-0.1.1.dist-info/top_level.txt
